EasyGA/EasyGA.py
EasyGA/__init__.py
EasyGA/attributes.py
EasyGA/decorators.py
EasyGA/crossover/Crossover.py
EasyGA/crossover/__init__.py
EasyGA/database/__init__.py
EasyGA/database/matplotlib_graph.py
EasyGA/database/sql_database.py
EasyGA/examples/Fitness.py
EasyGA/examples/__init__.py
EasyGA/mutation/Mutation.py
EasyGA/mutation/__init__.py
EasyGA/parent/Parent.py
EasyGA/parent/__init__.py
EasyGA/structure/__init__.py
EasyGA/structure/chromosome.py
EasyGA/structure/gene.py
EasyGA/structure/population.py
EasyGA/survivor/Survivor.py
EasyGA/survivor/__init__.py
EasyGA/termination/Termination.py
EasyGA/termination/__init__.py
EasyGA-1.6.1.dist-info/LICENSE.txt
EasyGA-1.6.1.dist-info/METADATA
EasyGA-1.6.1.dist-info/WHEEL
EasyGA-1.6.1.dist-info/top_level.txt
EasyGA-1.6.1.dist-info/RECORD
