Metadata-Version: 2.1
Name: EasyGA
Version: 1.6.1
Summary: EasyGA is a python package designed to provide an easy-to-use Genetic Algorithm. The package is designed to work right out of the box, while also allowing the user to customize features as they see fit.
Home-page: https://github.com/danielwilczak101/EasyGA
Author: Daniel Wilczak, Jack Nguyen, Ryley Griffith, Jared Curtis, Matthew Chase Oxamendi
Author-email: danielwilczak101@gmail.com
License: UNKNOWN
Platform: UNKNOWN
Requires-Python: >=3.6
